{
    "occurences_positions": {
        "0": [
            [
                59,
                108
            ],
            [
                145,
                194
            ],
            [
                307,
                356
            ],
            [
                664,
                713
            ]
        ],
        "1": [
            [
                44,
                93
            ],
            [
                130,
                179
            ],
            [
                292,
                341
            ],
            [
                649,
                698
            ]
        ]
    },
    "active_dims": {
        "0": [
            2,
            3,
            0,
            4
        ],
        "1": [
            0,
            2,
            3,
            4
        ]
    }
}