{
    "Data_filename": "armcoda_subject14_movement14.npy",
    "Patient_info": {
        "ID": 14,
        "Gender": "M",
        "Age": 23,
        "Height (cm)": 183.0,
        "Weight (kg)": 93.0,
        "BMI (kg/m^2)": 27.8,
        "Laterality": "R"
    },
    "Movement_info": {
        "movement_ID": 14,
        "Position": "Stand",
        "Movement": {
            "Limb": "Arm",
            "Laterality": "Left",
            "Action": "Elevation"
        },
        "Plan": "Scapular",
        "Hand": {
            "Laterality": null,
            "Position": null
        }
    },
    "Movement_label": {
        "Iteration_1": [
            41,
            1287
        ],
        "Iteration_2": [
            1438,
            2672
        ],
        "Iteration_3": [
            2811.0,
            4071.0
        ]
    }
}